{
  "report_time": {
    "iso": "2026-05-03T12:57:01Z",
    "unix": 1777813021.22,
    "date_dmy": "03-05-2026",
    "time_hm": "12:57",
    "version": "YCV-WX-MAM-HOLZ-03-05-IQ"
  },
  "outdoor": {
    "temperature_c": 16.7,
    "humidity_pct": 75,
    "feels_like_c": 16.3,
    "heat_index_c": 16.7
  },
  "wind": {
    "direction_code": "V E-WNW",
    "direction_full": "VARIABLE East AND West North-West",
    "current_direction": "WNW",
    "current_speed_kmh": 2,
    "avg_speed_kmh": 2.4,
    "gust_kmh": 1,
    "variable": true,
    "var_from": "E",
    "var_to": "WNW",
    "analysis_window_min": 30,
    "sample_count": 26
  },
  "rain": {
    "event_mm": 0.0,
    "daily_mm": 0.2,
    "total_mm": 0.0,
    "rate_mm_per_h": 0.0
  },
  "atmosphere": {
    "pressure_abs_hpa": 978,
    "pressure_qnh_hpa": 1009.7,
    "uv_index": 2,
    "light_klux": 14.16
  },
  "battery_pct": 100,
  "visibility": {
    "visibility_m": 16500,
    "visibility_source": "Open-Meteo API"
  }
}