{
  "report_time": {
    "iso": "2026-05-02T17:27:00Z",
    "unix": 1777742820.61,
    "date_dmy": "02-05-2026",
    "time_hm": "17:27",
    "version": "YCV-WX-MAM-HOLZ-02-05-HD"
  },
  "outdoor": {
    "temperature_c": 21.5,
    "humidity_pct": 39,
    "feels_like_c": 21.3,
    "heat_index_c": 21.5
  },
  "wind": {
    "direction_code": "SE",
    "direction_full": "South-East",
    "current_direction": "SE",
    "current_speed_kmh": 5,
    "avg_speed_kmh": 5.2,
    "gust_kmh": 4,
    "variable": false,
    "var_from": null,
    "var_to": null,
    "analysis_window_min": 30,
    "sample_count": 83
  },
  "rain": {
    "event_mm": 0.0,
    "daily_mm": 0.2,
    "total_mm": 0.0,
    "rate_mm_per_h": 0.0
  },
  "atmosphere": {
    "pressure_abs_hpa": 979,
    "pressure_qnh_hpa": 1010.2,
    "uv_index": 1,
    "light_klux": 6.15
  },
  "battery_pct": 100,
  "visibility": {
    "visibility_m": 39780,
    "visibility_source": "Open-Meteo API"
  }
}